MANIFEST.in
setup.cfg
setup.py
AppAutoTest/__init__.py
AppAutoTest/config.py
AppAutoTest/manage.py
AppAutoTest/root_dir.py
AppAutoTest/app/__init__.py
AppAutoTest/app/models.py
AppAutoTest/app/main/__init__.py
AppAutoTest/app/main/errors.py
AppAutoTest/app/main/forms.py
AppAutoTest/app/main/task.py
AppAutoTest/app/main/views.py
AppAutoTest/app/static/css/bootstrap-grid.css
AppAutoTest/app/static/css/bootstrap-grid.css.map
AppAutoTest/app/static/css/bootstrap-grid.min.css
AppAutoTest/app/static/css/bootstrap-grid.min.css.map
AppAutoTest/app/static/css/bootstrap-grid.rtl.css
AppAutoTest/app/static/css/bootstrap-grid.rtl.css.map
AppAutoTest/app/static/css/bootstrap-grid.rtl.min.css
AppAutoTest/app/static/css/bootstrap-grid.rtl.min.css.map
AppAutoTest/app/static/css/bootstrap-reboot.css
AppAutoTest/app/static/css/bootstrap-reboot.css.map
AppAutoTest/app/static/css/bootstrap-reboot.min.css
AppAutoTest/app/static/css/bootstrap-reboot.min.css.map
AppAutoTest/app/static/css/bootstrap-reboot.rtl.css
AppAutoTest/app/static/css/bootstrap-reboot.rtl.css.map
AppAutoTest/app/static/css/bootstrap-reboot.rtl.min.css
AppAutoTest/app/static/css/bootstrap-reboot.rtl.min.css.map
AppAutoTest/app/static/css/bootstrap-utilities.css
AppAutoTest/app/static/css/bootstrap-utilities.css.map
AppAutoTest/app/static/css/bootstrap-utilities.min.css
AppAutoTest/app/static/css/bootstrap-utilities.min.css.map
AppAutoTest/app/static/css/bootstrap-utilities.rtl.css
AppAutoTest/app/static/css/bootstrap-utilities.rtl.css.map
AppAutoTest/app/static/css/bootstrap-utilities.rtl.min.css
AppAutoTest/app/static/css/bootstrap-utilities.rtl.min.css.map
AppAutoTest/app/static/css/bootstrap.css
AppAutoTest/app/static/css/bootstrap.css.map
AppAutoTest/app/static/css/bootstrap.min.css
AppAutoTest/app/static/css/bootstrap.min.css.map
AppAutoTest/app/static/css/bootstrap.rtl.css
AppAutoTest/app/static/css/bootstrap.rtl.css.map
AppAutoTest/app/static/css/bootstrap.rtl.min.css
alex_app_auto_test.egg-info/PKG-INFO
alex_app_auto_test.egg-info/SOURCES.txt
alex_app_auto_test.egg-info/dependency_links.txt
alex_app_auto_test.egg-info/requires.txt
alex_app_auto_test.egg-info/top_level.txt