Metadata-Version: 2.1
Name: alex-app-auto-test
Version: 0.0.5
Summary: An app auto test
Home-page: UNKNOWN
Author: lixiaoyang
Author-email: 541121316@163.com
License: MIT Licence
Keywords: pip,alex_app_auto_test
Platform: any
